parted/__init__.py
parted/_parted.abi3.so
parted/alignment.py
parted/constraint.py
parted/device.py
parted/disk.py
parted/exceptions.py
parted/excpt.py
parted/filesys.py
parted/geom.py
parted/py.typed
parted/timer.py
parted/util.py
python_parted-1.1.1.dist-info/LICENSE
python_parted-1.1.1.dist-info/METADATA
python_parted-1.1.1.dist-info/WHEEL
python_parted-1.1.1.dist-info/RECORD
